{
  "id": 12,
  "alias": "Alistar",
  "name": "Alistar",
  "attackSpeed": 0.625,
  "splashCenteredImg": "cache/game/14.24/champion/Alistar/splashCentered.jpg",
  "splashImg": "cache/game/14.24/champion/Alistar/splash.jpg",
  "loadingImg": "cache/game/14.24/champion/Alistar/loading.png",
  "squareImg": "cache/game/14.24/champion/Alistar/square.png",
  "spells": [
    {
      "spellName": "Pulverize",
      "iconAsset": "cache/game/14.24/champion/Alistar/abilities/alistar_q.png",
      "iconName": "alistar_q.png"
    },
    {
      "spellName": "Headbutt",
      "iconAsset": "cache/game/14.24/champion/Alistar/abilities/alistar_w.png",
      "iconName": "alistar_w.png"
    },
    {
      "spellName": "AlistarE",
      "iconAsset": "cache/game/14.24/champion/Alistar/abilities/alistar_passive.png",
      "iconName": "alistar_passive.png"
    },
    {
      "spellName": "AlistarPassive",
      "iconAsset": "cache/game/14.24/champion/Alistar/abilities/alistar_e.png",
      "iconName": "alistar_e.png",
      "isPassive": true
    },
    {
      "spellName": "FerociousHowl",
      "iconAsset": "cache/game/14.24/champion/Alistar/abilities/alistar_r.png",
      "iconName": "alistar_r.png"
    }
  ]
}