{
  "id": 267,
  "alias": "Nami",
  "name": "Nami",
  "attackSpeed": 0.644,
  "splashCenteredImg": "cache/game/15.1/champion/Nami/splashCentered.jpg",
  "splashImg": "cache/game/15.1/champion/Nami/splash.jpg",
  "loadingImg": "cache/game/15.1/champion/Nami/loading.png",
  "squareImg": "cache/game/15.1/champion/Nami/square.png",
  "spells": [
    {
      "spellName": "NamiR",
      "iconAsset": "cache/game/15.1/champion/Nami/abilities/namir.png",
      "iconName": "namir.png"
    },
    {
      "spellName": "NamiQ",
      "iconAsset": "cache/game/15.1/champion/Nami/abilities/namiq.png",
      "iconName": "namiq.png"
    },
    {
      "spellName": "NamiQDebuff",
      "iconAsset": "cache/game/15.1/champion/Nami/abilities/ziggsq.png",
      "iconName": "ziggsq.png"
    },
    {
      "spellName": "NamiW",
      "iconAsset": "cache/game/15.1/champion/Nami/abilities/namiw.png",
      "iconName": "namiw.png"
    },
    {
      "spellName": "NamiWAlly",
      "iconAsset": "cache/game/15.1/champion/Nami/abilities/namiw.png",
      "iconName": "namiw.png"
    },
    {
      "spellName": "NamiWEnemy",
      "iconAsset": "cache/game/15.1/champion/Nami/abilities/namiw.png",
      "iconName": "namiw.png"
    },
    {
      "spellName": "NamiE",
      "iconAsset": "cache/game/15.1/champion/Nami/abilities/namie.png",
      "iconName": "namie.png"
    },
    {
      "spellName": "NamiPassive",
      "iconAsset": "cache/game/15.1/champion/Nami/abilities/namipassive.png",
      "iconName": "namipassive.png",
      "isPassive": true
    }
  ]
}