{
  "id": 517,
  "alias": "Sylas",
  "name": "Sylas",
  "attackSpeed": 0.645,
  "splashCenteredImg": "cache/game/14.24/champion/Sylas/splashCentered.jpg",
  "splashImg": "cache/game/14.24/champion/Sylas/splash.jpg",
  "loadingImg": "cache/game/14.24/champion/Sylas/loading.png",
  "squareImg": "cache/game/14.24/champion/Sylas/square.png",
  "spells": [
    {
      "spellName": "SylasR",
      "iconAsset": "cache/game/14.24/champion/Sylas/abilities/sylasr.png",
      "iconName": "sylasr.png"
    },
    {
      "spellName": "SylasQ",
      "iconAsset": "cache/game/14.24/champion/Sylas/abilities/sylasq.png",
      "iconName": "sylasq.png"
    },
    {
      "spellName": "SylasW",
      "iconAsset": "cache/game/14.24/champion/Sylas/abilities/sylasw.png",
      "iconName": "sylasw.png"
    },
    {
      "spellName": "SylasE",
      "iconAsset": "cache/game/14.24/champion/Sylas/abilities/sylase.png",
      "iconName": "sylase.png"
    },
    {
      "spellName": "SylasE2",
      "iconAsset": "cache/game/14.24/champion/Sylas/abilities/sylase2.png",
      "iconName": "sylase2.png"
    },
    {
      "spellName": "SylasEShield",
      "iconAsset": "cache/game/14.24/champion/Sylas/abilities/sylase.png",
      "iconName": "sylase.png"
    },
    {
      "spellName": "SylasPassive",
      "iconAsset": "cache/game/14.24/champion/Sylas/abilities/sylasp.png",
      "iconName": "sylasp.png",
      "isPassive": true
    }
  ]
}